deva_rich/__init__.py
deva_rich/grounded_segment_anything/.gitignore
deva_rich/grounded_segment_anything/.gitmodules
deva_rich/grounded_segment_anything/Dockerfile
deva_rich/grounded_segment_anything/LICENSE
deva_rich/grounded_segment_anything/Makefile
deva_rich/grounded_segment_anything/README.md
deva_rich/grounded_segment_anything/__init__.py
deva_rich/grounded_segment_anything/automatic_label_demo.py
deva_rich/grounded_segment_anything/automatic_label_ram_demo.py
deva_rich/grounded_segment_anything/automatic_label_simple_demo.py
deva_rich/grounded_segment_anything/automatic_label_tag2text_demo.py
deva_rich/grounded_segment_anything/chatbot.py
deva_rich/grounded_segment_anything/cog.yaml
deva_rich/grounded_segment_anything/gradio_app.py
deva_rich/grounded_segment_anything/grounded_sam.ipynb
deva_rich/grounded_segment_anything/grounded_sam_3d_box.ipynb
deva_rich/grounded_segment_anything/grounded_sam_colab_demo.ipynb
deva_rich/grounded_segment_anything/grounded_sam_demo.py
deva_rich/grounded_segment_anything/grounded_sam_inpainting_demo.py
deva_rich/grounded_segment_anything/grounded_sam_osx_demo.py
deva_rich/grounded_segment_anything/grounded_sam_simple_demo.py
deva_rich/grounded_segment_anything/grounded_sam_visam.py
deva_rich/grounded_segment_anything/grounded_sam_whisper_demo.py
deva_rich/grounded_segment_anything/grounded_sam_whisper_inpainting_demo.py
deva_rich/grounded_segment_anything/grounding_dino_demo.py
deva_rich/grounded_segment_anything/predict.py
deva_rich/grounded_segment_anything/requirements.txt
deva_rich/grounded_segment_anything/EfficientSAM/README.md
deva_rich/grounded_segment_anything/EfficientSAM/grounded_fast_sam.py
deva_rich/grounded_segment_anything/EfficientSAM/grounded_light_hqsam.py
deva_rich/grounded_segment_anything/EfficientSAM/grounded_mobile_sam.py
deva_rich/grounded_segment_anything/EfficientSAM/FastSAM/tools.py
deva_rich/grounded_segment_anything/EfficientSAM/LightHQSAM/example_light_hqsam.png
deva_rich-1.0.0.dist-info/METADATA
deva_rich-1.0.0.dist-info/WHEEL
deva_rich-1.0.0.dist-info/RECORD
